{
  "doc_id": "ComputerFund",
  "pipeline": "PACE-KG-v1",
  "total_slides": 14,
  "total_concepts": 28,
  "total_edges": 10,
  "relation_distribution": {
    "isPartOf": 3,
    "relatedConcept": 3,
    "contrastedWith": 2,
    "causeOf": 1,
    "isGeneralizationOf": 1
  },
  "nodes": [
    {
      "name": "digital computer",
      "aliases": [],
      "slide_ids": [
        "slide_013"
      ],
      "source_type": "bullet",
      "keyphrase_score": 0.9564,
      "final_weight": 0.6496,
      "needs_review": false
    },
    {
      "name": "general purpose computer",
      "aliases": [],
      "slide_ids": [
        "slide_013"
      ],
      "source_type": "bullet",
      "keyphrase_score": 0.9422,
      "final_weight": 0.548,
      "needs_review": false
    },
    {
      "name": "integrated circuits",
      "aliases": [],
      "slide_ids": [
        "slide_009"
      ],
      "source_type": "bullet",
      "keyphrase_score": 0.3797,
      "final_weight": 0.4903,
      "needs_review": false
    },
    {
      "name": "arithmetic operations",
      "aliases": [],
      "slide_ids": [
        "slide_010"
      ],
      "source_type": "body",
      "keyphrase_score": 0.6482,
      "final_weight": 0.441,
      "needs_review": false
    },
    {
      "name": "vlsi",
      "aliases": [],
      "slide_ids": [
        "slide_009"
      ],
      "source_type": "bullet",
      "keyphrase_score": 0.8135,
      "final_weight": 0.4289,
      "needs_review": false
    },
    {
      "name": "personal computer",
      "aliases": [],
      "slide_ids": [
        "slide_014"
      ],
      "source_type": "heading",
      "keyphrase_score": 0.7739,
      "final_weight": 0.3977,
      "needs_review": false
    },
    {
      "name": "capabilities of computer",
      "aliases": [],
      "slide_ids": [
        "slide_006"
      ],
      "source_type": "heading",
      "keyphrase_score": 0.7749,
      "final_weight": 0.3723,
      "needs_review": false
    },
    {
      "name": "difference between computer and calculator",
      "aliases": [],
      "slide_ids": [
        "slide_003"
      ],
      "source_type": "bullet",
      "keyphrase_score": 0.4238,
      "final_weight": 0.3499,
      "needs_review": false
    },
    {
      "name": "data processing",
      "aliases": [],
      "slide_ids": [
        "slide_005"
      ],
      "source_type": "bullet",
      "keyphrase_score": 0.7372,
      "final_weight": 0.3424,
      "needs_review": false
    },
    {
      "name": "logical operations",
      "aliases": [],
      "slide_ids": [
        "slide_010"
      ],
      "source_type": "body",
      "keyphrase_score": 0.5346,
      "final_weight": 0.3319,
      "needs_review": false
    },
    {
      "name": "types of computer",
      "aliases": [],
      "slide_ids": [
        "slide_003"
      ],
      "source_type": "bullet",
      "keyphrase_score": 0.6001,
      "final_weight": 0.3127,
      "needs_review": true
    },
    {
      "name": "microprocessor technology",
      "aliases": [],
      "slide_ids": [
        "slide_014"
      ],
      "source_type": "bullet",
      "keyphrase_score": 0.582,
      "final_weight": 0.2929,
      "needs_review": false
    },
    {
      "name": "mainframe computer",
      "aliases": [],
      "slide_ids": [
        "slide_013"
      ],
      "source_type": "bullet",
      "keyphrase_score": 0.8929,
      "final_weight": 0.2772,
      "needs_review": false
    },
    {
      "name": "storage capacity",
      "aliases": [],
      "slide_ids": [
        "slide_006"
      ],
      "source_type": "bullet",
      "keyphrase_score": 0.713,
      "final_weight": 0.2684,
      "needs_review": false
    },
    {
      "name": "micro computer",
      "aliases": [],
      "slide_ids": [
        "slide_013"
      ],
      "source_type": "bullet",
      "keyphrase_score": 0.9473,
      "final_weight": 0.2597,
      "needs_review": true
    },
    {
      "name": "type of pc",
      "aliases": [],
      "slide_ids": [
        "slide_003"
      ],
      "source_type": "bullet",
      "keyphrase_score": 0.6497,
      "final_weight": 0.2573,
      "needs_review": true
    },
    {
      "name": "cpu",
      "aliases": [],
      "slide_ids": [
        "slide_014"
      ],
      "source_type": "bullet",
      "keyphrase_score": 0.4407,
      "final_weight": 0.2573,
      "needs_review": false
    },
    {
      "name": "operations",
      "aliases": [],
      "slide_ids": [
        "slide_004"
      ],
      "source_type": "body",
      "keyphrase_score": 0.5556,
      "final_weight": 0.2455,
      "needs_review": false
    },
    {
      "name": "super computer",
      "aliases": [],
      "slide_ids": [
        "slide_013"
      ],
      "source_type": "bullet",
      "keyphrase_score": 0.9078,
      "final_weight": 0.2406,
      "needs_review": false
    },
    {
      "name": "anolog computer",
      "aliases": [],
      "slide_ids": [
        "slide_013"
      ],
      "source_type": "bullet",
      "keyphrase_score": 0.8962,
      "final_weight": 0.2395,
      "needs_review": false
    },
    {
      "name": "calculations",
      "aliases": [],
      "slide_ids": [
        "slide_004"
      ],
      "source_type": "body",
      "keyphrase_score": 0.5728,
      "final_weight": 0.2363,
      "needs_review": false
    },
    {
      "name": "processes",
      "aliases": [],
      "slide_ids": [
        "slide_004"
      ],
      "source_type": "body",
      "keyphrase_score": 0.4846,
      "final_weight": 0.2321,
      "needs_review": false
    },
    {
      "name": "hybrid computer",
      "aliases": [],
      "slide_ids": [
        "slide_013"
      ],
      "source_type": "bullet",
      "keyphrase_score": 0.9501,
      "final_weight": 0.2243,
      "needs_review": false
    },
    {
      "name": "mini computer",
      "aliases": [],
      "slide_ids": [
        "slide_013"
      ],
      "source_type": "bullet",
      "keyphrase_score": 0.9251,
      "final_weight": 0.2146,
      "needs_review": true
    },
    {
      "name": "apple os",
      "aliases": [],
      "slide_ids": [
        "slide_009"
      ],
      "source_type": "bullet",
      "keyphrase_score": 0.6579,
      "final_weight": 0.2077,
      "needs_review": false
    },
    {
      "name": "transistors",
      "aliases": [],
      "slide_ids": [
        "slide_009"
      ],
      "source_type": "bullet",
      "keyphrase_score": 0.3626,
      "final_weight": 0.2046,
      "needs_review": false
    },
    {
      "name": "instructions",
      "aliases": [],
      "slide_ids": [
        "slide_004"
      ],
      "source_type": "body",
      "keyphrase_score": 0.6681,
      "final_weight": 0.1959,
      "needs_review": false
    },
    {
      "name": "unix",
      "aliases": [],
      "slide_ids": [
        "slide_009"
      ],
      "source_type": "bullet",
      "keyphrase_score": 0.5278,
      "final_weight": 0.1942,
      "needs_review": false
    }
  ],
  "edges": [
    {
      "subject": "calculations",
      "relation": "isPartOf",
      "object": "processes",
      "evidence": "Definition A computer is an electronic machine or device that performs processes, calculations and operations based on instructions provided by a user.",
      "confidence": 0.9,
      "source": "extraction",
      "slide_id": "slide_004",
      "material_level": null
    },
    {
      "subject": "operations",
      "relation": "isPartOf",
      "object": "processes",
      "evidence": "Definition A computer is an electronic machine or device that performs processes, calculations and operations based on instructions provided by a user.",
      "confidence": 0.9,
      "source": "extraction",
      "slide_id": "slide_004",
      "material_level": null
    },
    {
      "subject": "arithmetic operations",
      "relation": "contrastedWith",
      "object": "logical operations",
      "evidence": "The main difference between Computer and Calculator is that the Computer is a simple general-purpose device for performing arithmetic or logical operations and Calculator is a electronic device used to perform arithmetic operations only.",
      "confidence": 0.8,
      "source": "extraction",
      "slide_id": "slide_010",
      "material_level": null
    },
    {
      "subject": "logical operations",
      "relation": "contrastedWith",
      "object": "arithmetic operations",
      "evidence": "The main difference between Computer and Calculator is that the Computer is a simple general-purpose device for performing arithmetic or logical operations and Calculator is a electronic device used to perform arithmetic operations only.",
      "confidence": 0.8,
      "source": "extraction",
      "slide_id": "slide_010",
      "material_level": null
    },
    {
      "subject": "instructions",
      "relation": "causeOf",
      "object": "processes",
      "evidence": "Definition A computer is an electronic machine or device that performs processes, calculations and operations based on instructions provided by a user.",
      "confidence": 0.7,
      "source": "extraction",
      "slide_id": "slide_004",
      "material_level": null
    },
    {
      "subject": "vlsi",
      "relation": "isPartOf",
      "object": "integrated circuits",
      "evidence": "Third Generation (1965-1974) Integrated Circuits Forth Generation (1975-1990) VLSI (Microprocessor), PC, semiconductor replaced magnetic core memories, Networking,DOS, Unix, Windows, Apple Os",
      "confidence": 0.7,
      "source": "extraction",
      "slide_id": "slide_009",
      "material_level": null
    },
    {
      "subject": "general purpose computer",
      "relation": "isGeneralizationOf",
      "object": "digital computer",
      "evidence": "On the basis of operating principles \u2713Digital computer \u2713Anolog Computer \u2713Hybrid Computer On the basis of applications \u2713General purpose computer",
      "confidence": 0.7,
      "source": "extraction",
      "slide_id": "slide_013",
      "material_level": null
    },
    {
      "subject": "digital computer",
      "relation": "relatedConcept",
      "object": "super computer",
      "evidence": null,
      "confidence": 0.6875,
      "source": "expansion",
      "slide_id": "slide_013",
      "material_level": null
    },
    {
      "subject": "digital computer",
      "relation": "relatedConcept",
      "object": "micro computer",
      "evidence": null,
      "confidence": 0.6823,
      "source": "expansion",
      "slide_id": "slide_013",
      "material_level": null
    },
    {
      "subject": "general purpose computer",
      "relation": "relatedConcept",
      "object": "mainframe computer",
      "evidence": null,
      "confidence": 0.6772,
      "source": "expansion",
      "slide_id": "slide_013",
      "material_level": null
    }
  ],
  "srs_pool": [
    {
      "triple_id": "t00001",
      "subject": "calculations",
      "relation": "isPartOf",
      "object": "processes",
      "evidence": "Definition A computer is an electronic machine or device that performs processes, calculations and operations based on instructions provided by a user.",
      "confidence": 0.9,
      "slide_id": "slide_004",
      "source": "extraction"
    },
    {
      "triple_id": "t00002",
      "subject": "operations",
      "relation": "isPartOf",
      "object": "processes",
      "evidence": "Definition A computer is an electronic machine or device that performs processes, calculations and operations based on instructions provided by a user.",
      "confidence": 0.9,
      "slide_id": "slide_004",
      "source": "extraction"
    },
    {
      "triple_id": "t00003",
      "subject": "arithmetic operations",
      "relation": "contrastedWith",
      "object": "logical operations",
      "evidence": "The main difference between Computer and Calculator is that the Computer is a simple general-purpose device for performing arithmetic or logical operations and Calculator is a electronic device used to perform arithmetic operations only.",
      "confidence": 0.8,
      "slide_id": "slide_010",
      "source": "extraction"
    },
    {
      "triple_id": "t00004",
      "subject": "logical operations",
      "relation": "contrastedWith",
      "object": "arithmetic operations",
      "evidence": "The main difference between Computer and Calculator is that the Computer is a simple general-purpose device for performing arithmetic or logical operations and Calculator is a electronic device used to perform arithmetic operations only.",
      "confidence": 0.8,
      "slide_id": "slide_010",
      "source": "extraction"
    },
    {
      "triple_id": "t00005",
      "subject": "instructions",
      "relation": "causeOf",
      "object": "processes",
      "evidence": "Definition A computer is an electronic machine or device that performs processes, calculations and operations based on instructions provided by a user.",
      "confidence": 0.7,
      "slide_id": "slide_004",
      "source": "extraction"
    },
    {
      "triple_id": "t00006",
      "subject": "vlsi",
      "relation": "isPartOf",
      "object": "integrated circuits",
      "evidence": "Third Generation (1965-1974) Integrated Circuits Forth Generation (1975-1990) VLSI (Microprocessor), PC, semiconductor replaced magnetic core memories, Networking,DOS, Unix, Windows, Apple Os",
      "confidence": 0.7,
      "slide_id": "slide_009",
      "source": "extraction"
    },
    {
      "triple_id": "t00007",
      "subject": "general purpose computer",
      "relation": "isGeneralizationOf",
      "object": "digital computer",
      "evidence": "On the basis of operating principles \u2713Digital computer \u2713Anolog Computer \u2713Hybrid Computer On the basis of applications \u2713General purpose computer",
      "confidence": 0.7,
      "slide_id": "slide_013",
      "source": "extraction"
    }
  ],
  "srs_pool_size": 7
}